puzzlepluginsystem-0.8.0.dist-info/licenses/LICENSE.txt
schwarz/puzzle_plugins/__init__.py
schwarz/puzzle_plugins/plugin_loader.py
schwarz/puzzle_plugins/signal_registry.py
puzzlepluginsystem-0.8.0.dist-info/METADATA
puzzlepluginsystem-0.8.0.dist-info/WHEEL
puzzlepluginsystem-0.8.0.dist-info/top_level.txt
puzzlepluginsystem-0.8.0.dist-info/RECORD
