Metadata-Version: 2.4
Name: PuzzlePluginSystem
Version: 0.8.0
Summary: generic plugin system based on setuptools and blinker
Home-page: https://github.com/FelixSchwarz/puzzle-plugin-system
Author: Felix Schwarz
Author-email: felix.schwarz@oss.schwarz.eu
License: MIT
Requires-Python: >=3.6
License-File: LICENSE.txt
Requires-Dist: blinker
Requires-Dist: importlib-metadata; python_version < "3.8"
Provides-Extra: testing
Requires-Dist: dotmap; extra == "testing"
Requires-Dist: pytest; extra == "testing"
Dynamic: license-file
